Metadata-Version: 2.1
Name: VSsetup
Version: 1.1
Summary: Use this tools to change the color of the outputs in the terminal
Author: Ruben Hinojar
License: MIT
License-File: LICENSE.txt
